chaintools/__init__.py
chaintools/core/__init__.py
chaintools/core/argument.py
chaintools/functional/__init__.py
chaintools/functional/function.py
chaintools/functional/types.py
chaintools-0.0.1.dist-info/LICENSE
chaintools-0.0.1.dist-info/METADATA
chaintools-0.0.1.dist-info/WHEEL
chaintools-0.0.1.dist-info/top_level.txt
chaintools-0.0.1.dist-info/RECORD
