Metadata-Version: 2.1
Name: chaintools
Version: 0.0.1
Summary: Replace nested function calls with chaining expression
Home-page: https://github.com/MaybeS/chaintools
Author: Jiun Bae
Author-email: jiunbae.dev@gmail.com
License: MIT
Download-URL: https://github.com/MaybeS/chaintools/releases/latest
Keywords: chaintools,functional
Platform: UNKNOWN
Classifier: Development Status :: 3 - Alpha
Classifier: Intended Audience :: Developers
Classifier: Operating System :: OS Independent
Classifier: Programming Language :: Python
Classifier: Programming Language :: Python :: 3
Classifier: Programming Language :: Python :: 3.6
Classifier: Programming Language :: Python :: 3.7
Classifier: Programming Language :: Python :: 3.8
Classifier: Topic :: Software Development :: Libraries :: Python Modules
Requires-Python: >= 3.6
